distilabel_steps_library/__init__.py
distilabel_steps_library/drop_empty.py
distilabel_steps_library/chat/__init__.py
distilabel_steps_library/chat/chat_transcript.py
distilabel_steps_library/chat/flip_role.py
distilabel_steps_library/chat/insert_message.py
distilabel_steps_library/chat/rewrite_messages.py
distilabel_steps_library/chat/save_to_jsonl.py
distilabel_steps_library-0.1.2.dist-info/METADATA
distilabel_steps_library-0.1.2.dist-info/WHEEL
distilabel_steps_library-0.1.2.dist-info/RECORD
